Metadata-Version: 2.4
Name: fuzzycategories
Version: 0.3.0
Summary: A generalised method of producing a soft hierarchy of soft clusters from a series of existing clusterings that have been generated using different representations of the same point-based data set.
Maintainer-email: William Oliver <william.hardie.oliver@gmail.com>
License: MIT
Classifier: Programming Language :: Python :: 3
Classifier: Operating System :: OS Independent
Classifier: License :: OSI Approved :: MIT License
Requires-Python: >=3.8
License-File: LICENSE.md
License-File: COPYING.md
Requires-Dist: numpy
Requires-Dist: numba
Requires-Dist: scikit-learn
Requires-Dist: hdbscan
Requires-Dist: astrolink
Requires-Dist: matplotlib
Provides-Extra: tests
Requires-Dist: pytest; extra == "tests"
Requires-Dist: pytest-cov; extra == "tests"
Requires-Dist: nbval; extra == "tests"
Provides-Extra: docs
Requires-Dist: ipykernel; extra == "docs"
Requires-Dist: nbsphinx; extra == "docs"
Requires-Dist: nbsphinx-link; extra == "docs"
Requires-Dist: sphinx; extra == "docs"
Requires-Dist: sphinx_mdinclude; extra == "docs"
Requires-Dist: sphinx_rtd_theme; extra == "docs"
Dynamic: license-file
